setup.py
docs/CUSTOMIZATON.txt
docs/HISTORY.txt
docs/INSTALL.txt
docs/LICENSE.GPL
docs/LICENSE.txt
docs/README.txt
docs/TODO.txt
vice/__init__.py
vice.plone.outbound.egg-info/PKG-INFO
vice.plone.outbound.egg-info/SOURCES.txt
vice.plone.outbound.egg-info/dependency_links.txt
vice.plone.outbound.egg-info/entry_points.txt
vice.plone.outbound.egg-info/namespace_packages.txt
vice.plone.outbound.egg-info/not-zip-safe
vice.plone.outbound.egg-info/requires.txt
vice.plone.outbound.egg-info/top_level.txt
vice/plone/__init__.py
vice/plone/outbound/README.txt
vice/plone/outbound/SyndicationTool.py
vice/plone/outbound/__init__.py
vice/plone/outbound/config.py
vice/plone/outbound/configlet.py
vice/plone/outbound/configure.zcml
vice/plone/outbound/interfaces.py
vice/plone/outbound/migrate.py
vice/plone/outbound/setuphandlers.py
vice/plone/outbound/Extensions/Install.py
vice/plone/outbound/adapters/__init__.py
vice/plone/outbound/adapters/atct.py
vice/plone/outbound/adapters/configure.zcml
vice/plone/outbound/browser/__init__.py
vice/plone/outbound/browser/autodiscover.pt
vice/plone/outbound/browser/autodiscover.py
vice/plone/outbound/browser/configfeed.py
vice/plone/outbound/browser/configure.zcml
vice/plone/outbound/browser/deactivate_config_kss.kss
vice/plone/outbound/browser/deactivate_config_kss.pt
vice/plone/outbound/browser/document.pt
vice/plone/outbound/browser/event.pt
vice/plone/outbound/browser/feed.py
vice/plone/outbound/browser/file.pt
vice/plone/outbound/browser/image.pt
vice/plone/outbound/browser/link.pt
vice/plone/outbound/browser/newsitem.pt
vice/plone/outbound/browser/vice.css
vice/plone/outbound/browser/view_feeds.pt
vice/plone/outbound/browser/viewfeeds.py
vice/plone/outbound/dtml/synOverview.dtml
vice/plone/outbound/dtml/synPolicies.dtml
vice/plone/outbound/dtml/synProps.dtml
vice/plone/outbound/dtml/synReports.dtml
vice/plone/outbound/feedformats/__init__.py
vice/plone/outbound/portlets/__init__.py
vice/plone/outbound/portlets/configure.zcml
vice/plone/outbound/portlets/feedlinks.pt
vice/plone/outbound/portlets/feedlinks.py
vice/plone/outbound/profiles/default/actionicons.xml
vice/plone/outbound/profiles/default/actions.xml
vice/plone/outbound/profiles/default/browserlayer.xml
vice/plone/outbound/profiles/default/componentregistry.xml
vice/plone/outbound/profiles/default/controlpanel.xml
