Metadata-Version: 1.0
Name: vice.plone.outbound
Version: 1.0rc1
Summary: Plone package for outbound syndication.
Home-page: http://www.openplans.org/projects/vice/
Author: Derek Richardson
Author-email: syndication@derekrichardson.net
License: GPL
Keywords: syndication atom rdf rss zope feeds plone
Platform: UNKNOWN
Classifier: Framework :: Plone
Classifier: Programming Language :: Python
Classifier: Topic :: Software Development :: Libraries :: Python Modules
